efficient_det/__init__.py
efficient_det/train.py
efficient_det/utils/__init__.py
efficient_det/utils/logs.py
my_test_pkg_tnfru-0.0.13.dist-info/LICENSE
my_test_pkg_tnfru-0.0.13.dist-info/METADATA
my_test_pkg_tnfru-0.0.13.dist-info/WHEEL
my_test_pkg_tnfru-0.0.13.dist-info/top_level.txt
my_test_pkg_tnfru-0.0.13.dist-info/RECORD
