Metadata-Version: 2.1
Name: my-test-pkg-tnfru
Version: 0.0.13
Summary: Brief test pkg
Home-page: https://github.com/pypa/sampleproject
Author: Lars Mueller
Author-email: lars.lmueller@gamil.com
License: UNKNOWN
Project-URL: Bug Tracker, https://github.com/pypa/sampleproject/issues
Platform: UNKNOWN
Classifier: Programming Language :: Python :: 3
Classifier: License :: OSI Approved :: Apache Software License
Classifier: Operating System :: OS Independent
Requires-Python: >=3.6.5
Requires-Dist: numpy (~=1.19.2)
Requires-Dist: tensorflow (>=2.4.0)
Requires-Dist: ray[tune]
Requires-Dist: matplotlib
Requires-Dist: wandb
Requires-Dist: focal-loss
Requires-Dist: pillow
